odoo/addons/shopfloor_checkout_putinpack_restriction/README.rst
odoo/addons/shopfloor_checkout_putinpack_restriction/__init__.py
odoo/addons/shopfloor_checkout_putinpack_restriction/__manifest__.py
odoo/addons/shopfloor_checkout_putinpack_restriction/actions/__init__.py
odoo/addons/shopfloor_checkout_putinpack_restriction/actions/message.py
odoo/addons/shopfloor_checkout_putinpack_restriction/i18n/it.po
odoo/addons/shopfloor_checkout_putinpack_restriction/i18n/shopfloor_checkout_putinpack_restriction.pot
odoo/addons/shopfloor_checkout_putinpack_restriction/readme/CONTRIBUTORS.rst
odoo/addons/shopfloor_checkout_putinpack_restriction/readme/DESCRIPTION.rst
odoo/addons/shopfloor_checkout_putinpack_restriction/services/__init__.py
odoo/addons/shopfloor_checkout_putinpack_restriction/services/checkout.py
odoo/addons/shopfloor_checkout_putinpack_restriction/static/description/icon.png
odoo/addons/shopfloor_checkout_putinpack_restriction/static/description/index.html
odoo/addons/shopfloor_checkout_putinpack_restriction/tests/__init__.py
odoo/addons/shopfloor_checkout_putinpack_restriction/tests/test_checkout_putinpack_restriction.py
odoo14_addon_shopfloor_checkout_putinpack_restriction-14.0.1.2.0.dist-info/METADATA
odoo14_addon_shopfloor_checkout_putinpack_restriction-14.0.1.2.0.dist-info/WHEEL
odoo14_addon_shopfloor_checkout_putinpack_restriction-14.0.1.2.0.dist-info/top_level.txt
odoo14_addon_shopfloor_checkout_putinpack_restriction-14.0.1.2.0.dist-info/RECORD
